README.md
setup.cfg
setup.py
py2sqlite3/Py2sqlite3.py
py2sqlite3/__init__.py
py2sqlite3/__main__.py
py2sqlite3/example.py
py2sqlite3.egg-info/PKG-INFO
py2sqlite3.egg-info/SOURCES.txt
py2sqlite3.egg-info/dependency_links.txt
py2sqlite3.egg-info/top_level.txt