Metadata-Version: 2.1
Name: py2sqlite3
Version: 0.17
Summary: py2sqlite3 is a library that facilitates the communication between python objects and sqlite3 databases.
Home-page: https://github.com/Vermillio/Metaprogramming2.0
Author: Vermillio
Author-email: morganas.scream@gmail.com
License: MIT
Download-URL: https://github.com/Vermillio/Metaprogramming2.0/archive/alpha.zip
Keywords: orm,sql,sqlite3,,C#,lexical analysis,parsing
Platform: UNKNOWN
Classifier: Development Status :: 3 - Alpha
Classifier: Intended Audience :: Developers
Classifier: License :: OSI Approved :: MIT License
Classifier: Programming Language :: Python :: 3.4
Classifier: Programming Language :: Python :: 3.5
Classifier: Programming Language :: Python :: 3.6
Classifier: Programming Language :: Python :: 3.7
Classifier: Programming Language :: Python :: 3.8
Requires-Python: >=3.6
